sg_api_py/__init__.py
sg_api_py/api.py
sg_api_py-0.1.6.dist-info/licenses/LICENSE
sg_api_py-0.1.6.dist-info/METADATA
sg_api_py-0.1.6.dist-info/WHEEL
sg_api_py-0.1.6.dist-info/top_level.txt
sg_api_py-0.1.6.dist-info/RECORD
