Metadata-Version: 2.4
Name: sg-api.py
Version: 0.1.6
Summary: A python API wrapper for the Squid Game API
Author-email: stainlesteel <pd4500@protonmail.com>
Project-URL: Homepage, https://github.com/stainlesteel/sg_api.py
Project-URL: Issues, https://github.com/stainlesteel/sg_api.py/issues
Classifier: Programming Language :: Python :: 3
Classifier: License :: OSI Approved :: MIT License
Classifier: Operating System :: OS Independent
Requires-Python: >=3.8
License-File: LICENSE
Dynamic: license-file
